ttp/__init__.py
ttp/emoji.py
ttp/en_emoji.py
ttp/unicode_codes/__init__.py
turkish-twitter-preprocess/__init__.py
turkish_twitter_preprocess-0.0.7.dist-info/LICENSE
turkish_twitter_preprocess-0.0.7.dist-info/METADATA
turkish_twitter_preprocess-0.0.7.dist-info/WHEEL
turkish_twitter_preprocess-0.0.7.dist-info/top_level.txt
turkish_twitter_preprocess-0.0.7.dist-info/RECORD
