Metadata-Version: 2.1
Name: turkish-twitter-preprocess
Version: 0.0.7
Summary: a light-weight python package to pre-process turkish twitter statuses(tweets).
Home-page: https://github.com/emskaplann/turkish-twitter-preprocess
Author: Emirhan Kaplan
Author-email: emskaplann@gmail.com
License: UNKNOWN
Keywords: turkish twitter preprocess
Platform: UNKNOWN
Classifier: Programming Language :: Python :: 3
Classifier: License :: OSI Approved :: MIT License
Classifier: Operating System :: OS Independent
Requires-Python: >=2.7
